Metadata-Version: 2.1
Name: topsis-101703550
Version: 1.1.0
Summary: A Python package to rank ML models/choices using topsis technique
Home-page: https://github.com/simratbrar/topsis-package
Author: Simrat Bir Singh
Author-email: simratbir4@gmail.com
License: MIT
Platform: UNKNOWN
Classifier: License :: OSI Approved :: MIT License
Classifier: Programming Language :: Python :: 3
Classifier: Programming Language :: Python :: 3.7
